odoo/addons/purchase_start_end_dates/README.rst
odoo/addons/purchase_start_end_dates/__init__.py
odoo/addons/purchase_start_end_dates/__manifest__.py
odoo/addons/purchase_start_end_dates/i18n/it.po
odoo/addons/purchase_start_end_dates/i18n/purchase_start_end_dates.pot
odoo/addons/purchase_start_end_dates/models/__init__.py
odoo/addons/purchase_start_end_dates/models/purchase_order.py
odoo/addons/purchase_start_end_dates/readme/CONTRIBUTORS.md
odoo/addons/purchase_start_end_dates/readme/DESCRIPTION.md
odoo/addons/purchase_start_end_dates/static/description/icon.png
odoo/addons/purchase_start_end_dates/static/description/index.html
odoo/addons/purchase_start_end_dates/tests/__init__.py
odoo/addons/purchase_start_end_dates/tests/test_purchase_start_end_dates.py
odoo/addons/purchase_start_end_dates/views/purchase_order.xml
odoo_addon_purchase_start_end_dates-17.0.1.0.0.3.dist-info/METADATA
odoo_addon_purchase_start_end_dates-17.0.1.0.0.3.dist-info/WHEEL
odoo_addon_purchase_start_end_dates-17.0.1.0.0.3.dist-info/top_level.txt
odoo_addon_purchase_start_end_dates-17.0.1.0.0.3.dist-info/RECORD
